benchmarks/__init__.py
benchmarks/arithmetic_ops.py
benchmarks/boolean.py
benchmarks/comparison_ops.py
benchmarks/take.py
benchmarks/text.py
fletcher/__init__.py
fletcher/_algorithms.py
fletcher/_compat.py
fletcher/_dask_compat.py
fletcher/base.py
fletcher/io.py
fletcher/string_array.py
fletcher/string_mixin.py
fletcher/testing.py
fletcher/algorithms/__init__.py
fletcher/algorithms/bool.py
fletcher/algorithms/numpy_ufunc.py
fletcher/algorithms/string.py
fletcher/algorithms/string_builder.py
fletcher/algorithms/string_builder_nojit.py
fletcher/algorithms/utils/__init__.py
fletcher/algorithms/utils/chunking.py
fletcher/algorithms/utils/kmp.py
fletcher-0.7.2.dist-info/LICENSE
fletcher-0.7.2.dist-info/METADATA
fletcher-0.7.2.dist-info/NOTICE
fletcher-0.7.2.dist-info/WHEEL
fletcher-0.7.2.dist-info/top_level.txt
fletcher-0.7.2.dist-info/RECORD
