Metadata-Version: 2.1
Name: fletcher
Version: 0.7.2
Summary: Pandas ExtensionDType/Array backed by Apache Arrow
Home-page: https://github.com/xhochy/fletcher
Author: Uwe L. Korn
Author-email: fletcher@uwekorn.com
License: MIT
Platform: UNKNOWN
Classifier: License :: OSI Approved :: MIT License
Classifier: Programming Language :: Python :: 2
Classifier: Programming Language :: Python :: 2.7
Classifier: Programming Language :: Python :: 3
Classifier: Programming Language :: Python :: 3.5
Classifier: Programming Language :: Python :: 3.6
Requires-Python: >=3
Requires-Dist: pandas (>=1.0)
Requires-Dist: pyarrow (>=0.17.0)
Requires-Dist: numba (>=0.49)
Requires-Dist: six
